tomboulier_foobar/__init__.py
tomboulier_foobar/__main__.py
tomboulier_foobar-0.2.0.dist-info/LICENSE
tomboulier_foobar-0.2.0.dist-info/WHEEL
tomboulier_foobar-0.2.0.dist-info/METADATA
tomboulier_foobar-0.2.0.dist-info/RECORD
