Metadata-Version: 2.1
Name: tomboulier-foobar
Version: 0.2.0
Summary: This is a simple 'Hello, world!' example for the purpose of showing how Flit works.
Author-email: Thomas Boulier <boulier.thomas@gmail.com>
Classifier: License :: OSI Approved :: MIT License
Project-URL: Home, https://github.com/tomboulier/flit-demo
